postgresdbmodel/__init__.py
postgresdbmodel/postgres_dal.py
postgresdbmodel/sqlalchemy_data_mapper.py
postgresdbmodel-0.1.1.dist-info/licenses/LICENSE
postgresdbmodel-0.1.1.dist-info/METADATA
postgresdbmodel-0.1.1.dist-info/WHEEL
postgresdbmodel-0.1.1.dist-info/top_level.txt
postgresdbmodel-0.1.1.dist-info/RECORD
