Metadata-Version: 2.4
Name: postgresdbmodel
Version: 0.1.1
Summary: Capa de acceso a datos para PostgreSQL integrada con SQLAlchemy
Author: darth wayne
Author-email: darrthwayne@gmail.com
Requires-Python: >=3.7
License-File: LICENSE
Requires-Dist: SQLAlchemy
Requires-Dist: psycopg2-binary
Dynamic: author
Dynamic: author-email
Dynamic: description
Dynamic: description-content-type
Dynamic: license-file
Dynamic: requires-dist
Dynamic: requires-python
Dynamic: summary
